jps_controlled_vocabularies_utils/__init__.py
jps_controlled_vocabularies_utils/exceptions.py
jps_controlled_vocabularies_utils/parser.py
jps_controlled_vocabularies_utils/record.py
jps_controlled_vocabularies_utils/registry.py
jps_controlled_vocabularies_utils/results.py
jps_controlled_vocabularies_utils/validator.py
jps_controlled_vocabularies_utils/vocabulary.py
jps_controlled_vocabularies_utils/io/__init__.py
jps_controlled_vocabularies_utils/io/source.py
jps_controlled_vocabularies_utils/io/yaml_loader.py
jps_controlled_vocabularies_utils/utils/__init__.py
jps_controlled_vocabularies_utils/utils/normalize.py
jps_controlled_vocabularies_utils-0.1.0.dist-info/licenses/LICENSE
jps_controlled_vocabularies_utils-0.1.0.dist-info/METADATA
jps_controlled_vocabularies_utils-0.1.0.dist-info/WHEEL
jps_controlled_vocabularies_utils-0.1.0.dist-info/top_level.txt
jps_controlled_vocabularies_utils-0.1.0.dist-info/RECORD
